Metadata-Version: 2.1
Name: trivy-to-google-sheets
Version: 0.4.0
Summary: A tool to run Trivy scans and export results to Google Sheets
Home-page: https://github.com/joseEnrique/trivy-to-google-sheets
Author: Quique Ruiz
Author-email: joseenriqueruiznavarro@gmail.com
Classifier: Programming Language :: Python :: 3
Classifier: License :: OSI Approved :: MIT License
Classifier: Operating System :: OS Independent
Requires-Python: >=3.6
Requires-Dist: gspread>=5.7.1
Requires-Dist: oauth2client>=4.1.3
Requires-Dist: google-api-python-client>=2.92.0
